griffe_kirin/__init__.py
griffe_kirin-0.2.0.dist-info/METADATA
griffe_kirin-0.2.0.dist-info/WHEEL
griffe_kirin-0.2.0.dist-info/licenses/LICENSE
griffe_kirin-0.2.0.dist-info/RECORD
