Metadata-Version: 2.4
Name: griffe-kirin
Version: 0.2.0
Summary: Griffe plugin for Kirin
Author-email: Roger-luo <rluo@quera.com>
License-File: LICENSE
Requires-Python: >=3.10
Requires-Dist: griffe>=1.5.6
Requires-Dist: typing-extensions>=4.12.2
